daisynt/__init__.py
daisynt-0.0.2.dist-info/METADATA
daisynt-0.0.2.dist-info/WHEEL
daisynt-0.0.2.dist-info/license.txt
daisynt-0.0.2.dist-info/top_level.txt
daisynt-0.0.2.dist-info/RECORD
