Metadata-Version: 2.1
Name: daisynt
Version: 0.0.2
Summary: Test Suite to enable Synthetic Data adoption
Author: Giacomo Graffi
Author-email: giacomo.graffi@gmail.com
License: UNKNOWN
Platform: UNKNOWN
Requires-Python: >=3.6
License-File: license.txt
